odoo/addons/account_invoice_blocking/README.rst
odoo/addons/account_invoice_blocking/__init__.py
odoo/addons/account_invoice_blocking/__manifest__.py
odoo/addons/account_invoice_blocking/i18n/account_invoice_blocking.pot
odoo/addons/account_invoice_blocking/i18n/de.po
odoo/addons/account_invoice_blocking/i18n/es.po
odoo/addons/account_invoice_blocking/i18n/hr.po
odoo/addons/account_invoice_blocking/i18n/it.po
odoo/addons/account_invoice_blocking/i18n/nl.po
odoo/addons/account_invoice_blocking/i18n/pt.po
odoo/addons/account_invoice_blocking/i18n/pt_BR.po
odoo/addons/account_invoice_blocking/models/__init__.py
odoo/addons/account_invoice_blocking/models/account_move.py
odoo/addons/account_invoice_blocking/readme/CONTRIBUTORS.md
odoo/addons/account_invoice_blocking/readme/DESCRIPTION.md
odoo/addons/account_invoice_blocking/readme/ROADMAP.md
odoo/addons/account_invoice_blocking/readme/USAGE.md
odoo/addons/account_invoice_blocking/static/description/icon.png
odoo/addons/account_invoice_blocking/static/description/index.html
odoo/addons/account_invoice_blocking/tests/__init__.py
odoo/addons/account_invoice_blocking/tests/test_account_move_blocking.py
odoo/addons/account_invoice_blocking/views/account_move.xml
odoo_addon_account_invoice_blocking-17.0.1.0.2.dist-info/METADATA
odoo_addon_account_invoice_blocking-17.0.1.0.2.dist-info/WHEEL
odoo_addon_account_invoice_blocking-17.0.1.0.2.dist-info/top_level.txt
odoo_addon_account_invoice_blocking-17.0.1.0.2.dist-info/RECORD
