Metadata-Version: 2.1
Name: odoo-addon-account_invoice_blocking
Version: 17.0.1.0.2
Requires-Python: >=3.10
Requires-Dist: odoo>=17.0a,<17.1dev
Summary: Set a blocking (No Follow-up) flag on invoices
Home-page: https://github.com/OCA/account-invoicing
License: AGPL-3
Author: Acsone SA/NV,Odoo Community Association (OCA)
Author-email: support@odoo-community.org
Classifier: Programming Language :: Python
Classifier: Framework :: Odoo
Classifier: Framework :: Odoo :: 17.0
Classifier: License :: OSI Approved :: GNU Affero General Public License v3
